synthetic_videos/__init__.py
synthetic_videos/heygen/__init__.py
synthetic_videos/heygen/models.py
synthetic_videos/heygen/sas.py
synthetic_videos/heygen/video.py
synthetic_videos/pjlogging/__init__.py
synthetic_videos/pjlogging/logger.py
synthetic_videos/synthesia/__init__.py
synthetic_videos/synthesia/models.py
synthetic_videos/synthesia/video.py
synthetic_videos/synthetic_videos_interface.py
synthetic_videos/utils/__init__.py
synthetic_videos/utils/utils.py
synthetic_videos-2.0.0.dist-info/entry_points.txt
synthetic_videos-2.0.0.dist-info/LICENSE.txt
synthetic_videos-2.0.0.dist-info/METADATA
synthetic_videos-2.0.0.dist-info/WHEEL
synthetic_videos-2.0.0.dist-info/RECORD
