Metadata-Version: 2.1
Name: synthetic_videos
Version: 2.0.0
Summary: Python project to generate synthetic videos for the pipeline project
Home-page: https://www.profjim.com
Author: Prof Jim Inc
Requires-Python: >=3.8,<3.13
Classifier: Development Status :: 5 - Production/Stable
Classifier: Intended Audience :: Developers
Classifier: License :: OSI Approved :: MIT License
Classifier: Operating System :: OS Independent
Classifier: Programming Language :: Python
Classifier: Programming Language :: Python :: 3
Classifier: Programming Language :: Python :: 3.8
Classifier: Programming Language :: Python :: 3.9
Classifier: Programming Language :: Python :: 3.10
Classifier: Programming Language :: Python :: 3.11
Classifier: Programming Language :: Python :: 3.12
Classifier: Programming Language :: Python :: 3 :: Only
Classifier: Typing :: Typed
Requires-Dist: loguru (>=0.7.2,<0.8.0)
Requires-Dist: rich
Requires-Dist: typer[all]
Project-URL: Documentation, https://www.profjim.com
Project-URL: Repository, https://www.profjim.com
